{
  "recentFiles": [
    {
      "basename": "電気電子系",
      "path": "00 Index/電気電子系.md"
    },
    {
      "basename": "数学・物理",
      "path": "00 Index/数学・物理.md"
    },
    {
      "basename": "情報系",
      "path": "00 Index/情報系.md"
    },
    {
      "basename": "四力&制御",
      "path": "00 Index/四力&制御.md"
    },
    {
      "basename": "1_機械システム工学科情報機械プログラム",
      "path": "00 Index/1_機械システム工学科情報機械プログラム.md"
    },
    {
      "basename": "システム系",
      "path": "00 Index/システム系.md"
    },
    {
      "basename": "機械設計・製図",
      "path": "00 Index/機械設計・製図.md"
    },
    {
      "basename": "信号処理",
      "path": "Note/デジタル信号処理/知識/信号処理.md"
    }
  ],
  "omittedPaths": [],
  "maxLength": null,
  "openType": "tab"
}